remly/__init__.py
remly/__main__.py
remly/main.py
remly/remly.py
remly/network/__init__.py
remly/network/arp.py
remly/network/utils.py
remly-2.0.0.dist-info/LICENSE
remly-2.0.0.dist-info/METADATA
remly-2.0.0.dist-info/WHEEL
remly-2.0.0.dist-info/entry_points.txt
remly-2.0.0.dist-info/top_level.txt
remly-2.0.0.dist-info/RECORD
