Metadata-Version: 2.1
Name: remly
Version: 2.0.0
Summary: Small python library and CLI script which allows running computers remotely on LAN.
Home-page: https://github.com/sectasy0/remly
Author: Piotr Markiewicz
Author-email: sectasy0@gmail.com
License: MIT License
Keywords: remly
Platform: UNKNOWN
